handcalcs/__init__.py
handcalcs/config.json
handcalcs/constants.py
handcalcs/conversion_funcs.py
handcalcs/decorator.py
handcalcs/global_config.py
handcalcs/handcalcs.py
handcalcs/integrations.py
handcalcs/py.typed
handcalcs/render.py
handcalcs/sympy_kit.py
handcalcs/handcalcs_html/__init__.py
handcalcs/handcalcs_html/classic/base.html.j2
handcalcs/handcalcs_html/classic/conf.json
handcalcs/handcalcs_html/classic/index.html.j2
handcalcs/handcalcs_html/classic/static/style.css
handcalcs-1.10.0.dist-info/licenses/LICENSE
handcalcs-1.10.0.dist-info/WHEEL
handcalcs-1.10.0.dist-info/METADATA
handcalcs-1.10.0.dist-info/RECORD
