Metadata-Version: 2.4
Name: handcalcs
Version: 1.10.0
Summary: Render arithmetic calucations in Jupyter as though they were written by hand.
Author-email: Connor Ferster <connorferster@gmail.com>
Classifier: License :: OSI Approved :: Apache Software License
License-File: LICENSE
Requires-Dist: more_itertools
Requires-Dist: innerscope >= 0.7.0
Requires-Dist: pyparsing
Requires-Dist: sphinx ; extra == "doc"
Requires-Dist: nb-hideinputs ; extra == "exporters"
Project-URL: Source, https://github.com/connorferster/handcalcs
Provides-Extra: doc
Provides-Extra: exporters
